executor_dkr/__init__.py
executor_dkr/_config.py
executor_dkr/_impl.py
executor_dkr/cli.py
executor_dkr-0.0.7.dist-info/METADATA
executor_dkr-0.0.7.dist-info/WHEEL
executor_dkr-0.0.7.dist-info/entry_points.txt
executor_dkr-0.0.7.dist-info/top_level.txt
executor_dkr-0.0.7.dist-info/RECORD
