Metadata-Version: 2.1
Name: executor-dkr
Version: 0.0.7
Summary: DaggerML's front end for the docker executor
Author-email: DaggerML <engineering@daggerml.com>
Project-URL: Homepage, https://daggerml.com
Project-URL: Documentation, https://daggerml.com/docs
Project-URL: Issues, https://github.com/daggerml/python-lib/issues
Classifier: License :: OSI Approved :: MIT License
Classifier: Operating System :: OS Independent
Classifier: Development Status :: 4 - Beta
Classifier: Programming Language :: Python :: 3
Classifier: Programming Language :: Python :: 3.6
Classifier: Programming Language :: Python :: 3.7
Classifier: Programming Language :: Python :: 3.8
Classifier: Programming Language :: Python :: 3.9
Classifier: Programming Language :: Python :: 3.10
Classifier: Programming Language :: Python :: 3.11
Requires-Python: >=3.6
Requires-Dist: daggerml (>=0.0.15)
Provides-Extra: all
Requires-Dist: executor-s3 (>=0.0.9) ; extra == 'all'
Provides-Extra: s3
Requires-Dist: executor-s3 (>=0.0.9) ; extra == 's3'
